bindcurve/__init__.py
bindcurve/calculate.py
bindcurve/data.py
bindcurve/models.py
bindcurve/models_other.py
bindcurve-0.1.2.dist-info/licenses/LICENSE
bindcurve-0.1.2.dist-info/METADATA
bindcurve-0.1.2.dist-info/WHEEL
bindcurve-0.1.2.dist-info/top_level.txt
bindcurve-0.1.2.dist-info/RECORD
