Metadata-Version: 2.4
Name: bindcurve
Version: 0.1.2
Summary: A Python package for fitting and plotting of binding curves.
Author-email: Jan Choutka <jan.choutka@uochb.cas.cz>
License-Expression: MIT
Requires-Python: >=3.8
License-File: LICENSE
Requires-Dist: numpy
Requires-Dist: pandas
Requires-Dist: matplotlib
Requires-Dist: lmfit
Dynamic: license-file
